qena_shared_lib/__init__.py
qena_shared_lib/alias.py
qena_shared_lib/application.py
qena_shared_lib/background.py
qena_shared_lib/cache.py
qena_shared_lib/dependencies/__init__.py
qena_shared_lib/dependencies/http.py
qena_shared_lib/dependencies/miscellaneous.py
qena_shared_lib/enums.py
qena_shared_lib/eventbus.py
qena_shared_lib/exception_handling.py
qena_shared_lib/exceptions.py
qena_shared_lib/http/__init__.py
qena_shared_lib/http/_base.py
qena_shared_lib/http/_exception_handlers.py
qena_shared_lib/http/_request.py
qena_shared_lib/http/_response.py
qena_shared_lib/kafka/__init__.py
qena_shared_lib/kafka/_base.py
qena_shared_lib/kafka/_consumer.py
qena_shared_lib/kafka/_exception_handlers.py
qena_shared_lib/kafka/_producer.py
qena_shared_lib/logging.py
qena_shared_lib/mongodb.py
qena_shared_lib/py.typed
qena_shared_lib/rabbitmq/__init__.py
qena_shared_lib/rabbitmq/_base.py
qena_shared_lib/rabbitmq/_channel.py
qena_shared_lib/rabbitmq/_exception_handlers.py
qena_shared_lib/rabbitmq/_listener.py
qena_shared_lib/rabbitmq/_pool.py
qena_shared_lib/rabbitmq/_publisher.py
qena_shared_lib/rabbitmq/_rpc_client.py
qena_shared_lib/rabbitmq/message/__init__.py
qena_shared_lib/rabbitmq/message/_inbound.py
qena_shared_lib/rabbitmq/message/_outbound.py
qena_shared_lib/redis.py
qena_shared_lib/remotelogging/__init__.py
qena_shared_lib/remotelogging/_base.py
qena_shared_lib/remotelogging/logstash/__init__.py
qena_shared_lib/remotelogging/logstash/_base.py
qena_shared_lib/remotelogging/logstash/_http_sender.py
qena_shared_lib/remotelogging/logstash/_tcp_sender.py
qena_shared_lib/scheduler.py
qena_shared_lib/security.py
qena_shared_lib/sync.py
qena_shared_lib/utils.py
qena_shared_lib-0.1.23.dist-info/WHEEL
qena_shared_lib-0.1.23.dist-info/METADATA
qena_shared_lib-0.1.23.dist-info/RECORD
