Metadata-Version: 2.3
Name: qena-shared-lib
Version: 0.1.23
Summary: A shared tools for other services
Requires-Dist: fastapi[all]==0.115.6
Requires-Dist: prometheus-client==0.21.1
Requires-Dist: prometheus-fastapi-instrumentator==7.0.2
Requires-Dist: punq==0.7.0
Requires-Dist: pydantic-core==2.27.1
Requires-Dist: pydantic==2.10.3
Requires-Dist: starlette==0.41.3
Requires-Dist: typing-extensions==4.12.2
Requires-Dist: aiokafka==0.12.0 ; extra == 'all'
Requires-Dist: cronsim==2.6 ; extra == 'all'
Requires-Dist: jwt==1.3.1 ; extra == 'all'
Requires-Dist: passlib[bcrypt]==1.7.4 ; extra == 'all'
Requires-Dist: pika==1.3.2 ; extra == 'all'
Requires-Dist: pymongo==4.15.3 ; extra == 'all'
Requires-Dist: redis==7.1.0 ; extra == 'all'
Requires-Dist: aiokafka==0.12.0 ; extra == 'kafka'
Requires-Dist: pymongo==4.15.3 ; extra == 'mongodb'
Requires-Dist: pika==1.3.2 ; extra == 'rabbitmq'
Requires-Dist: redis==7.1.0 ; extra == 'redis'
Requires-Dist: cronsim==2.6 ; extra == 'scheduler'
Requires-Dist: jwt==1.3.1 ; extra == 'security'
Requires-Dist: passlib[bcrypt]==1.7.4 ; extra == 'security'
Requires-Python: >=3.10
Provides-Extra: all
Provides-Extra: kafka
Provides-Extra: mongodb
Provides-Extra: rabbitmq
Provides-Extra: redis
Provides-Extra: scheduler
Provides-Extra: security
